LICENSE
MANIFEST.in
README.md
setup.cfg
setup.py
subzerod/__init__.py
subzerod/agents.py
subzerod/cli.py
subzerod/sites.py
subzerod/subzerod.py
subzerod/utils.py
subzerod/web.py
subzerod.egg-info/PKG-INFO
subzerod.egg-info/SOURCES.txt
subzerod.egg-info/dependency_links.txt
subzerod.egg-info/entry_points.txt
subzerod.egg-info/not-zip-safe
subzerod.egg-info/requires.txt
subzerod.egg-info/top_level.txt