Metadata-Version: 2.1
Name: subzerod
Version: 1.0
Summary: Subdomain enumeration tool
Home-page: https://github.com/sanderfoobar/subzerod
Author: Sander
Author-email: sander@sanderf.nl
License: WTFPL
Keywords: subdomain pentesting pentest security
Platform: any
Classifier: Environment :: Console
Classifier: Intended Audience :: Information Technology
Classifier: Intended Audience :: System Administrators
Classifier: Intended Audience :: Telecommunications Industry
Classifier: Operating System :: POSIX :: Linux
Classifier: Programming Language :: Python :: 3
Classifier: Programming Language :: Python :: 3.6
Classifier: Programming Language :: Python :: 3.7
Classifier: Programming Language :: Python :: 3.8
Classifier: Topic :: Security
Requires-Python: >=3.6
